{"nodes": [{"id": "c_users_lksferreira_documents_github_game_of_turing_metadocs_walkthrough_renomeacao_jogador_md", "label": "renomeacao_jogador.md", "file_type": "document", "source_file": "C:\\Users\\LKSFERREIRA\\Documents\\GitHub\\game-of-turing\\.metadocs\\walkthrough\\renomeacao_jogador.md", "source_location": "L1"}, {"id": "walkthrough_renomeacao_jogador_walkthrough_renomea\u00e7\u00e3o_de_interlocutor_para_jogador", "label": "Walkthrough: Renomea\u00e7\u00e3o de Interlocutor para Jogador", "file_type": "document", "source_file": "C:\\Users\\LKSFERREIRA\\Documents\\GitHub\\game-of-turing\\.metadocs\\walkthrough\\renomeacao_jogador.md", "source_location": "L1"}, {"id": "walkthrough_renomeacao_jogador_contexto_da_demanda", "label": "Contexto da Demanda", "file_type": "document", "source_file": "C:\\Users\\LKSFERREIRA\\Documents\\GitHub\\game-of-turing\\.metadocs\\walkthrough\\renomeacao_jogador.md", "source_location": "L5"}, {"id": "walkthrough_renomeacao_jogador_mudan\u00e7as_realizadas", "label": "Mudan\u00e7as Realizadas", "file_type": "document", "source_file": "C:\\Users\\LKSFERREIRA\\Documents\\GitHub\\game-of-turing\\.metadocs\\walkthrough\\renomeacao_jogador.md", "source_location": "L9"}, {"id": "walkthrough_renomeacao_jogador_1_dom\u00ednio_domain_jogo", "label": "1. Dom\u00ednio (`domain/jogo/`)", "file_type": "document", "source_file": "C:\\Users\\LKSFERREIRA\\Documents\\GitHub\\game-of-turing\\.metadocs\\walkthrough\\renomeacao_jogador.md", "source_location": "L13"}, {"id": "walkthrough_renomeacao_jogador_2_testes_unit\u00e1rios_domain_jogo_jogo_test_ts", "label": "2. Testes Unit\u00e1rios (`domain/jogo/jogo.test.ts`)", "file_type": "document", "source_file": "C:\\Users\\LKSFERREIRA\\Documents\\GitHub\\game-of-turing\\.metadocs\\walkthrough\\renomeacao_jogador.md", "source_location": "L20"}, {"id": "walkthrough_renomeacao_jogador_3_apis_e_interfaces_app", "label": "3. APIs e Interfaces (`app/`)", "file_type": "document", "source_file": "C:\\Users\\LKSFERREIRA\\Documents\\GitHub\\game-of-turing\\.metadocs\\walkthrough\\renomeacao_jogador.md", "source_location": "L24"}, {"id": "walkthrough_renomeacao_jogador_4_banco_de_dados_e_nomenclaturas_em_ingl\u00eas", "label": "4. Banco de Dados e Nomenclaturas em Ingl\u00eas", "file_type": "document", "source_file": "C:\\Users\\LKSFERREIRA\\Documents\\GitHub\\game-of-turing\\.metadocs\\walkthrough\\renomeacao_jogador.md", "source_location": "L29"}, {"id": "walkthrough_renomeacao_jogador_5_documenta\u00e7\u00e3o_geral", "label": "5. Documenta\u00e7\u00e3o Geral", "file_type": "document", "source_file": "C:\\Users\\LKSFERREIRA\\Documents\\GitHub\\game-of-turing\\.metadocs\\walkthrough\\renomeacao_jogador.md", "source_location": "L33"}, {"id": "walkthrough_renomeacao_jogador_valida\u00e7\u00e3o_executada", "label": "Valida\u00e7\u00e3o Executada", "file_type": "document", "source_file": "C:\\Users\\LKSFERREIRA\\Documents\\GitHub\\game-of-turing\\.metadocs\\walkthrough\\renomeacao_jogador.md", "source_location": "L37"}, {"id": "walkthrough_renomeacao_jogador_codeblock_1", "label": "code:text (\u2713 domain/jogo/jogo.test.ts (10 tests) 16ms)", "file_type": "document", "source_file": "C:\\Users\\LKSFERREIRA\\Documents\\GitHub\\game-of-turing\\.metadocs\\walkthrough\\renomeacao_jogador.md", "source_location": "L41"}], "edges": [{"source": "c_users_lksferreira_documents_github_game_of_turing_metadocs_walkthrough_renomeacao_jogador_md", "target": "walkthrough_renomeacao_jogador_walkthrough_renomea\u00e7\u00e3o_de_interlocutor_para_jogador", "relation": "contains", "confidence": "EXTRACTED", "source_file": "C:\\Users\\LKSFERREIRA\\Documents\\GitHub\\game-of-turing\\.metadocs\\walkthrough\\renomeacao_jogador.md", "source_location": "L1", "weight": 1.0}, {"source": "walkthrough_renomeacao_jogador_walkthrough_renomea\u00e7\u00e3o_de_interlocutor_para_jogador", "target": "walkthrough_renomeacao_jogador_contexto_da_demanda", "relation": "contains", "confidence": "EXTRACTED", "source_file": "C:\\Users\\LKSFERREIRA\\Documents\\GitHub\\game-of-turing\\.metadocs\\walkthrough\\renomeacao_jogador.md", "source_location": "L5", "weight": 1.0}, {"source": "walkthrough_renomeacao_jogador_walkthrough_renomea\u00e7\u00e3o_de_interlocutor_para_jogador", "target": "walkthrough_renomeacao_jogador_mudan\u00e7as_realizadas", "relation": "contains", "confidence": "EXTRACTED", "source_file": "C:\\Users\\LKSFERREIRA\\Documents\\GitHub\\game-of-turing\\.metadocs\\walkthrough\\renomeacao_jogador.md", "source_location": "L9", "weight": 1.0}, {"source": "walkthrough_renomeacao_jogador_mudan\u00e7as_realizadas", "target": "walkthrough_renomeacao_jogador_1_dom\u00ednio_domain_jogo", "relation": "contains", "confidence": "EXTRACTED", "source_file": "C:\\Users\\LKSFERREIRA\\Documents\\GitHub\\game-of-turing\\.metadocs\\walkthrough\\renomeacao_jogador.md", "source_location": "L13", "weight": 1.0}, {"source": "walkthrough_renomeacao_jogador_mudan\u00e7as_realizadas", "target": "walkthrough_renomeacao_jogador_2_testes_unit\u00e1rios_domain_jogo_jogo_test_ts", "relation": "contains", "confidence": "EXTRACTED", "source_file": "C:\\Users\\LKSFERREIRA\\Documents\\GitHub\\game-of-turing\\.metadocs\\walkthrough\\renomeacao_jogador.md", "source_location": "L20", "weight": 1.0}, {"source": "walkthrough_renomeacao_jogador_mudan\u00e7as_realizadas", "target": "walkthrough_renomeacao_jogador_3_apis_e_interfaces_app", "relation": "contains", "confidence": "EXTRACTED", "source_file": "C:\\Users\\LKSFERREIRA\\Documents\\GitHub\\game-of-turing\\.metadocs\\walkthrough\\renomeacao_jogador.md", "source_location": "L24", "weight": 1.0}, {"source": "walkthrough_renomeacao_jogador_mudan\u00e7as_realizadas", "target": "walkthrough_renomeacao_jogador_4_banco_de_dados_e_nomenclaturas_em_ingl\u00eas", "relation": "contains", "confidence": "EXTRACTED", "source_file": "C:\\Users\\LKSFERREIRA\\Documents\\GitHub\\game-of-turing\\.metadocs\\walkthrough\\renomeacao_jogador.md", "source_location": "L29", "weight": 1.0}, {"source": "walkthrough_renomeacao_jogador_mudan\u00e7as_realizadas", "target": "walkthrough_renomeacao_jogador_5_documenta\u00e7\u00e3o_geral", "relation": "contains", "confidence": "EXTRACTED", "source_file": "C:\\Users\\LKSFERREIRA\\Documents\\GitHub\\game-of-turing\\.metadocs\\walkthrough\\renomeacao_jogador.md", "source_location": "L33", "weight": 1.0}, {"source": "walkthrough_renomeacao_jogador_walkthrough_renomea\u00e7\u00e3o_de_interlocutor_para_jogador", "target": "walkthrough_renomeacao_jogador_valida\u00e7\u00e3o_executada", "relation": "contains", "confidence": "EXTRACTED", "source_file": "C:\\Users\\LKSFERREIRA\\Documents\\GitHub\\game-of-turing\\.metadocs\\walkthrough\\renomeacao_jogador.md", "source_location": "L37", "weight": 1.0}, {"source": "walkthrough_renomeacao_jogador_valida\u00e7\u00e3o_executada", "target": "walkthrough_renomeacao_jogador_codeblock_1", "relation": "contains", "confidence": "EXTRACTED", "source_file": "C:\\Users\\LKSFERREIRA\\Documents\\GitHub\\game-of-turing\\.metadocs\\walkthrough\\renomeacao_jogador.md", "source_location": "L41", "weight": 1.0}], "input_tokens": 0, "output_tokens": 0}