{"nodes": [{"id": "c_users_lksferreira_documents_github_game_of_turing_domain_jogo_estatisticas_ts", "label": "estatisticas.ts", "file_type": "code", "source_file": "C:\\Users\\LKSFERREIRA\\Documents\\GitHub\\game-of-turing\\domain\\jogo\\estatisticas.ts", "source_location": "L1"}, {"id": "jogo_estatisticas_estatisticasparticipante", "label": "EstatisticasParticipante", "file_type": "code", "source_file": "C:\\Users\\LKSFERREIRA\\Documents\\GitHub\\game-of-turing\\domain\\jogo\\estatisticas.ts", "source_location": "L3"}, {"id": "jogo_estatisticas_contarpalavras", "label": "contarPalavras()", "file_type": "code", "source_file": "C:\\Users\\LKSFERREIRA\\Documents\\GitHub\\game-of-turing\\domain\\jogo\\estatisticas.ts", "source_location": "L12"}, {"id": "jogo_estatisticas_calcularestatisticasparticipante", "label": "calcularEstatisticasParticipante()", "file_type": "code", "source_file": "C:\\Users\\LKSFERREIRA\\Documents\\GitHub\\game-of-turing\\domain\\jogo\\estatisticas.ts", "source_location": "L23"}], "edges": [{"source": "c_users_lksferreira_documents_github_game_of_turing_domain_jogo_estatisticas_ts", "target": "c_users_lksferreira_documents_github_game_of_turing_domain_jogo_tipos_ts", "relation": "imports_from", "context": "import", "confidence": "EXTRACTED", "source_file": "C:\\Users\\LKSFERREIRA\\Documents\\GitHub\\game-of-turing\\domain\\jogo\\estatisticas.ts", "source_location": "L1", "weight": 1.0}, {"source": "c_users_lksferreira_documents_github_game_of_turing_domain_jogo_estatisticas_ts", "target": "jogo_tipos_mensagempartida", "relation": "imports", "context": "import", "confidence": "EXTRACTED", "source_file": "C:\\Users\\LKSFERREIRA\\Documents\\GitHub\\game-of-turing\\domain\\jogo\\estatisticas.ts", "source_location": "L1", "weight": 1.0}, {"source": "c_users_lksferreira_documents_github_game_of_turing_domain_jogo_estatisticas_ts", "target": "jogo_tipos_participantepartida", "relation": "imports", "context": "import", "confidence": "EXTRACTED", "source_file": "C:\\Users\\LKSFERREIRA\\Documents\\GitHub\\game-of-turing\\domain\\jogo\\estatisticas.ts", "source_location": "L1", "weight": 1.0}, {"source": "c_users_lksferreira_documents_github_game_of_turing_domain_jogo_estatisticas_ts", "target": "jogo_tipos_partida", "relation": "imports", "context": "import", "confidence": "EXTRACTED", "source_file": "C:\\Users\\LKSFERREIRA\\Documents\\GitHub\\game-of-turing\\domain\\jogo\\estatisticas.ts", "source_location": "L1", "weight": 1.0}, {"source": "c_users_lksferreira_documents_github_game_of_turing_domain_jogo_estatisticas_ts", "target": "jogo_estatisticas_estatisticasparticipante", "relation": "contains", "confidence": "EXTRACTED", "source_file": "C:\\Users\\LKSFERREIRA\\Documents\\GitHub\\game-of-turing\\domain\\jogo\\estatisticas.ts", "source_location": "L3", "weight": 1.0}, {"source": "c_users_lksferreira_documents_github_game_of_turing_domain_jogo_estatisticas_ts", "target": "jogo_estatisticas_contarpalavras", "relation": "contains", "confidence": "EXTRACTED", "source_file": "C:\\Users\\LKSFERREIRA\\Documents\\GitHub\\game-of-turing\\domain\\jogo\\estatisticas.ts", "source_location": "L12", "weight": 1.0}, {"source": "c_users_lksferreira_documents_github_game_of_turing_domain_jogo_estatisticas_ts", "target": "jogo_estatisticas_calcularestatisticasparticipante", "relation": "contains", "confidence": "EXTRACTED", "source_file": "C:\\Users\\LKSFERREIRA\\Documents\\GitHub\\game-of-turing\\domain\\jogo\\estatisticas.ts", "source_location": "L23", "weight": 1.0}, {"source": "jogo_estatisticas_calcularestatisticasparticipante", "target": "jogo_estatisticas_contarpalavras", "relation": "calls", "context": "call", "confidence": "EXTRACTED", "source_file": "C:\\Users\\LKSFERREIRA\\Documents\\GitHub\\game-of-turing\\domain\\jogo\\estatisticas.ts", "source_location": "L30", "weight": 1.0}], "raw_calls": [{"caller_nid": "jogo_estatisticas_contarpalavras", "callee": "reduce", "is_member_call": true, "source_file": "C:\\Users\\LKSFERREIRA\\Documents\\GitHub\\game-of-turing\\domain\\jogo\\estatisticas.ts", "source_location": "L13"}, {"caller_nid": "jogo_estatisticas_calcularestatisticasparticipante", "callee": "filter", "is_member_call": true, "source_file": "C:\\Users\\LKSFERREIRA\\Documents\\GitHub\\game-of-turing\\domain\\jogo\\estatisticas.ts", "source_location": "L27"}, {"caller_nid": "jogo_estatisticas_calcularestatisticasparticipante", "callee": "max", "is_member_call": true, "source_file": "C:\\Users\\LKSFERREIRA\\Documents\\GitHub\\game-of-turing\\domain\\jogo\\estatisticas.ts", "source_location": "L31"}, {"caller_nid": "jogo_estatisticas_calcularestatisticasparticipante", "callee": "round", "is_member_call": true, "source_file": "C:\\Users\\LKSFERREIRA\\Documents\\GitHub\\game-of-turing\\domain\\jogo\\estatisticas.ts", "source_location": "L34"}, {"caller_nid": "jogo_estatisticas_calcularestatisticasparticipante", "callee": "Number", "is_member_call": false, "source_file": "C:\\Users\\LKSFERREIRA\\Documents\\GitHub\\game-of-turing\\domain\\jogo\\estatisticas.ts", "source_location": "L43"}, {"caller_nid": "jogo_estatisticas_calcularestatisticasparticipante", "callee": "toFixed", "is_member_call": true, "source_file": "C:\\Users\\LKSFERREIRA\\Documents\\GitHub\\game-of-turing\\domain\\jogo\\estatisticas.ts", "source_location": "L43"}]}